fuel_agent/__init__.py
fuel_agent/errors.py
fuel_agent/hooks.py
fuel_agent/manager.py
fuel_agent/version.py
fuel_agent/cmd/__init__.py
fuel_agent/cmd/agent.py
fuel_agent/cmd/ironic_callback.py
fuel_agent/drivers/__init__.py
fuel_agent/drivers/base.py
fuel_agent/drivers/bootstrap.py
fuel_agent/drivers/ks_spaces_validator.py
fuel_agent/drivers/nailgun.py
fuel_agent/drivers/simple.py
fuel_agent/objects/__init__.py
fuel_agent/objects/base.py
fuel_agent/objects/bootloader.py
fuel_agent/objects/configdrive.py
fuel_agent/objects/device.py
fuel_agent/objects/image.py
fuel_agent/objects/operating_system.py
fuel_agent/objects/repo.py
fuel_agent/objects/users.py
fuel_agent/objects/partition/__init__.py
fuel_agent/objects/partition/fs.py
fuel_agent/objects/partition/lv.py
fuel_agent/objects/partition/md.py
fuel_agent/objects/partition/parted.py
fuel_agent/objects/partition/pv.py
fuel_agent/objects/partition/scheme.py
fuel_agent/objects/partition/vg.py
fuel_agent/openstack/__init__.py
fuel_agent/tests/__init__.py
fuel_agent/tests/base.py
fuel_agent/tests/test_artifact_utils.py
fuel_agent/tests/test_build_utils.py
fuel_agent/tests/test_configdrive.py
fuel_agent/tests/test_fs_utils.py
fuel_agent/tests/test_grub_utils.py
fuel_agent/tests/test_hardware_utils.py
fuel_agent/tests/test_image.py
fuel_agent/tests/test_ks_spaces_validator.py
fuel_agent/tests/test_lvm_utils.py
fuel_agent/tests/test_manager.py
fuel_agent/tests/test_md_utils.py
fuel_agent/tests/test_nailgun.py
fuel_agent/tests/test_nailgun_build_image.py
fuel_agent/tests/test_partition.py
fuel_agent/tests/test_partition_utils.py
fuel_agent/tests/test_provision_utils.py
fuel_agent/tests/test_requirements.py
fuel_agent/tests/test_simple_nailgun_driver.py
fuel_agent/tests/test_utils.py
fuel_agent/tests/fixtures/simple_nailgun_driver.json
fuel_agent/utils/__init__.py
fuel_agent/utils/artifact.py
fuel_agent/utils/build.py
fuel_agent/utils/decorators.py
fuel_agent-11.0.0.dist-info/DESCRIPTION.rst
fuel_agent-11.0.0.dist-info/METADATA
fuel_agent-11.0.0.dist-info/RECORD
fuel_agent-11.0.0.dist-info/WHEEL
fuel_agent-11.0.0.dist-info/entry_points.txt
fuel_agent-11.0.0.dist-info/metadata.json
fuel_agent-11.0.0.dist-info/pbr.json
fuel_agent-11.0.0.dist-info/top_level.txt
